oneNeuronUploader/__init__.py
oneNeuronUploader/main.py
oneNeuronUploader/setup.py
oneNeuronUploader/src/__init__.py
oneNeuronUploader/src/upload_video.py
oneNeuronUploader/src/utils/__init__.py
oneNeuronUploader/src/utils/all_utils.py
oneNeuronUploader/src/utils/upload_manager.py
oneNeuronUploader/static/css/assets/img/img.jpeg
oneNeuronUploader/templates/error.html
oneNeuronUploader/templates/index.html
oneNeuronUploader/templates/upload.html
oneNeuronUploader-0.2.dist-info/LICENSE.txt
oneNeuronUploader-0.2.dist-info/METADATA
oneNeuronUploader-0.2.dist-info/WHEEL
oneNeuronUploader-0.2.dist-info/entry_points.txt
oneNeuronUploader-0.2.dist-info/top_level.txt
oneNeuronUploader-0.2.dist-info/RECORD
