Metadata-Version: 2.1
Name: oneNeuronUploader
Version: 0.2
Summary: Its an auto video uploading library
Home-page: https://github.com/entbappy/oneNeuronUploader
Author: Bappy Ahmed
Author-email: entbappy73@gmail.com
License: MIT
Keywords: oneNeuronUploader
Platform: UNKNOWN
Classifier: Development Status :: 3 - Alpha
Classifier: Intended Audience :: Developers
Classifier: Topic :: Software Development :: Build Tools
Classifier: License :: OSI Approved :: MIT License
Classifier: Programming Language :: Python :: 3
Classifier: Programming Language :: Python :: 3.4
Classifier: Programming Language :: Python :: 3.5
Classifier: Programming Language :: Python :: 3.6
License-File: LICENSE.txt
Requires-Dist: PyVimeo (==1.1.0)
Requires-Dist: PyYAML (==6.0)
Requires-Dist: Flask-Cors
Requires-Dist: Flask
